ProgramizSwiftJiaochengChuyiFix1/README.md
ProgramizSwiftJiaochengChuyiFix1/__init__.py
ProgramizSwiftJiaochengChuyiFix1/__main__.py
ProgramizSwiftJiaochengChuyiFix1/file.epub
ProgramizSwiftJiaochengChuyiFix1/index.html
ProgramizSwiftJiaochengChuyiFix1/css/__init__.py
ProgramizSwiftJiaochengChuyiFix1/css/annotations.css
ProgramizSwiftJiaochengChuyiFix1/css/main.css
ProgramizSwiftJiaochengChuyiFix1/css/normalize.css
ProgramizSwiftJiaochengChuyiFix1/css/popup.css
ProgramizSwiftJiaochengChuyiFix1/font/__init__.py
ProgramizSwiftJiaochengChuyiFix1/font/fontello.eot
ProgramizSwiftJiaochengChuyiFix1/font/fontello.svg
ProgramizSwiftJiaochengChuyiFix1/font/fontello.ttf
ProgramizSwiftJiaochengChuyiFix1/font/fontello.woff
ProgramizSwiftJiaochengChuyiFix1/img/__init__.py
ProgramizSwiftJiaochengChuyiFix1/img/annotator-glyph-sprite.png
ProgramizSwiftJiaochengChuyiFix1/img/annotator-icon-sprite.png
ProgramizSwiftJiaochengChuyiFix1/img/apple-touch-icon.png
ProgramizSwiftJiaochengChuyiFix1/img/cancelfullscreen.png
ProgramizSwiftJiaochengChuyiFix1/img/close.png
ProgramizSwiftJiaochengChuyiFix1/img/fullscreen.png
ProgramizSwiftJiaochengChuyiFix1/img/loader.gif
ProgramizSwiftJiaochengChuyiFix1/img/menu-icon.png
ProgramizSwiftJiaochengChuyiFix1/img/save.png
ProgramizSwiftJiaochengChuyiFix1/img/saved.png
ProgramizSwiftJiaochengChuyiFix1/img/settings-s.png
ProgramizSwiftJiaochengChuyiFix1/img/settings.png
ProgramizSwiftJiaochengChuyiFix1/img/star.png
ProgramizSwiftJiaochengChuyiFix1/js/__init__.py
ProgramizSwiftJiaochengChuyiFix1/js/epub.js
ProgramizSwiftJiaochengChuyiFix1/js/epub.min.js
ProgramizSwiftJiaochengChuyiFix1/js/epub.min.map
ProgramizSwiftJiaochengChuyiFix1/js/hooks.min.js
ProgramizSwiftJiaochengChuyiFix1/js/hooks.min.map
ProgramizSwiftJiaochengChuyiFix1/js/reader.js
ProgramizSwiftJiaochengChuyiFix1/js/reader.js.map
ProgramizSwiftJiaochengChuyiFix1/js/reader.min.js
ProgramizSwiftJiaochengChuyiFix1/js/reader.min.map
ProgramizSwiftJiaochengChuyiFix1/js/hooks/__init__.py
programiz_swift_jiaocheng_chuyi_fix1-2025.3.24.0.dist-info/METADATA
programiz_swift_jiaocheng_chuyi_fix1-2025.3.24.0.dist-info/WHEEL
programiz_swift_jiaocheng_chuyi_fix1-2025.3.24.0.dist-info/entry_points.txt
programiz_swift_jiaocheng_chuyi_fix1-2025.3.24.0.dist-info/top_level.txt
programiz_swift_jiaocheng_chuyi_fix1-2025.3.24.0.dist-info/RECORD
